seqreport/SeqCollection.py
seqreport/__init__.py
seqreport/reports.py
seqreport/report_assets/report_style.css
seqreport/report_assets/seq_report.pug
seqreport-0.1.2.dist-info/licenses/LICENSE
seqreport-0.1.2.dist-info/METADATA
seqreport-0.1.2.dist-info/WHEEL
seqreport-0.1.2.dist-info/top_level.txt
seqreport-0.1.2.dist-info/RECORD
