Metadata-Version: 2.4
Name: seqreport
Version: 0.1.2
Summary: Simple reporting on a set of sequences for documentation purposes
Author: Peter Vegh
License-Expression: MIT
Project-URL: Homepage, https://github.com/Edinburgh-Genome-Foundry/Seq_Report
Keywords: biology,dna
License-File: LICENSE
Requires-Dist: biopython
Requires-Dist: pdf_reports
Dynamic: license-file
